odoo/addons/currency_rate_update_banxico/README.rst
odoo/addons/currency_rate_update_banxico/__init__.py
odoo/addons/currency_rate_update_banxico/__manifest__.py
odoo/addons/currency_rate_update_banxico/i18n/currency_rate_update_banxico.pot
odoo/addons/currency_rate_update_banxico/i18n/es.po
odoo/addons/currency_rate_update_banxico/models/__init__.py
odoo/addons/currency_rate_update_banxico/models/res_currency_rate_provider_banxico.py
odoo/addons/currency_rate_update_banxico/readme/CONFIGURE.md
odoo/addons/currency_rate_update_banxico/readme/CONTRIBUTORS.md
odoo/addons/currency_rate_update_banxico/readme/DESCRIPTION.md
odoo/addons/currency_rate_update_banxico/static/description/icon.png
odoo/addons/currency_rate_update_banxico/static/description/index.html
odoo/addons/currency_rate_update_banxico/tests/__init__.py
odoo/addons/currency_rate_update_banxico/tests/test_currency_rate_update_banxico.py
odoo/addons/currency_rate_update_banxico/views/res_currency_rate_provider_views.xml
odoo_addon_currency_rate_update_banxico-18.0.1.0.0.3.dist-info/METADATA
odoo_addon_currency_rate_update_banxico-18.0.1.0.0.3.dist-info/WHEEL
odoo_addon_currency_rate_update_banxico-18.0.1.0.0.3.dist-info/top_level.txt
odoo_addon_currency_rate_update_banxico-18.0.1.0.0.3.dist-info/RECORD
