Metadata-Version: 2.1
Name: odoo-addon-currency_rate_update_banxico
Version: 18.0.1.0.0.3
Requires-Python: >=3.10
Requires-Dist: odoo-addon-currency_rate_update==18.0.*
Requires-Dist: odoo==18.0.*
Requires-Dist: requests-mock
Summary: Update exchange rates using Banxico
Home-page: https://github.com/OCA/l10n-mexico
License: AGPL-3
Author: Jarsa, AMOdoo, Odoo Community Association (OCA)
Author-email: support@odoo-community.org
Classifier: Programming Language :: Python
Classifier: Framework :: Odoo
Classifier: Framework :: Odoo :: 18.0
Classifier: License :: OSI Approved :: GNU Affero General Public License v3
